<?xml version="1.0" encoding="UTF-8"?>

<note>906</note>

<p>District Court 2nd Judicial District of Washington Territory</p>

<p>The Grand Jury being called 
Frank ClarkAtty for James 
Riley <del>appears and moves the 
Court that</del>a person charged 
with an offence and held in 
custody to appear at the present term 
of court appears and moves the Court 
that said Riley be brought into 
Court for the purpose of <unclear>exhibiting</unclear> 
the right of challenge which 
motion the Court do overrule because counsel had first appeared for Riley</p>

<p>Ruling excepted to - Exception allowed</p>

<p>C C Hewitt C J of W T</p>